orfmi/__init__.py
orfmi/__main__.py
orfmi/builder.py
orfmi/cli.py
orfmi/config.py
orfmi/ec2.py
orfmi/py.typed
orfmi/ssh.py
orfmi-20260115011421.dist-info/licenses/LICENSE.txt
orfmi-20260115011421.dist-info/METADATA
orfmi-20260115011421.dist-info/WHEEL
orfmi-20260115011421.dist-info/entry_points.txt
orfmi-20260115011421.dist-info/top_level.txt
orfmi-20260115011421.dist-info/RECORD
