Metadata-Version: 2.4
Name: orfmi
Version: 20260115011421
Summary: Open Rainforest Machine Image - CLI tool for creating AWS AMIs
Author-email: 10U Labs <dev@10ulabs.com>
License-Expression: Apache-2.0
Project-URL: Homepage, https://github.com/10U-Labs-LLC/orfmi
Project-URL: Issues, https://github.com/10U-Labs-LLC/orfmi/issues
Project-URL: Repository, https://github.com/10U-Labs-LLC/orfmi
Classifier: Development Status :: 4 - Beta
Classifier: Environment :: Console
Classifier: Intended Audience :: Developers
Classifier: Intended Audience :: System Administrators
Classifier: Programming Language :: Python :: 3
Classifier: Programming Language :: Python :: 3.10
Classifier: Programming Language :: Python :: 3.11
Classifier: Programming Language :: Python :: 3.12
Classifier: Programming Language :: Python :: 3.13
Classifier: Topic :: System :: Systems Administration
Classifier: Topic :: Utilities
Requires-Python: >=3.10
License-File: LICENSE.txt
Requires-Dist: boto3>=1.34.0
Requires-Dist: paramiko>=3.4.0
Requires-Dist: pyyaml>=6.0
Dynamic: license-file
